aerovaldb/__init__.py
aerovaldb/aerovaldb.py
aerovaldb/const.py
aerovaldb/exceptions.py
aerovaldb/plugins.py
aerovaldb/routes.py
aerovaldb/types.py
aerovaldb/jsondb/__init__.py
aerovaldb/jsondb/backwards_compatibility.py
aerovaldb/jsondb/cache.py
aerovaldb/jsondb/jsonfiledb.py
aerovaldb/lock/__init__.py
aerovaldb/lock/lock.py
aerovaldb/sqlitedb/__init__.py
aerovaldb/sqlitedb/sqlitedb.py
aerovaldb/utils/__init__.py
aerovaldb/utils/asyncio.py
aerovaldb/utils/copy.py
aerovaldb/utils/encode.py
aerovaldb/utils/filter.py
aerovaldb/utils/json.py
aerovaldb/utils/query.py
aerovaldb/utils/string_utils.py
aerovaldb/utils/uri.py
aerovaldb/utils/string_mapper/__init__.py
aerovaldb/utils/string_mapper/mapper.py
aerovaldb-0.5.0.dist-info/licenses/LICENSE
aerovaldb-0.5.0.dist-info/METADATA
aerovaldb-0.5.0.dist-info/WHEEL
aerovaldb-0.5.0.dist-info/entry_points.txt
aerovaldb-0.5.0.dist-info/top_level.txt
aerovaldb-0.5.0.dist-info/RECORD
