Metadata-Version: 2.4
Name: aerovaldb
Version: 0.5.0
Summary: aeroval database to communicate between pyaerocom and aeroval
Home-page: https://github.com/metno/aerovaldb
Author: Augustin Mortier, Thorbjørn Lundin, Heiko Klein
Author-email: Heiko.Klein@met.no
Classifier: Programming Language :: Python :: 3 :: Only
Classifier: Programming Language :: Python :: 3.10
Classifier: Programming Language :: Python :: 3.11
Classifier: Programming Language :: Python :: 3.12
Classifier: Programming Language :: Python :: 3.13
Classifier: License :: OSI Approved :: GNU General Public License v3 (GPLv3)
Classifier: Operating System :: OS Independent
Classifier: Development Status :: 4 - Beta
Classifier: Intended Audience :: Science/Research
Classifier: Intended Audience :: Education
Classifier: Topic :: Scientific/Engineering :: Atmospheric Science
License-File: LICENSE
Requires-Dist: importlib-metadata>=3.6; python_version < "3.10"
Requires-Dist: simplejson
Requires-Dist: async_lru
Requires-Dist: packaging
Requires-Dist: filetype
Requires-Dist: typing-extensions; python_version < "3.12"
Dynamic: license-file
